setup.py
YatfsRpc.egg-info/PKG-INFO
YatfsRpc.egg-info/SOURCES.txt
YatfsRpc.egg-info/dependency_links.txt
YatfsRpc.egg-info/entry_points.txt
YatfsRpc.egg-info/top_level.txt
yatfs_plugin/__init__.py
yatfs_plugin/core.py