Metadata-Version: 1.1
Name: YatfsRpc
Version: 1.0.1
Summary: RPC helper plugin for YATFS.
Home-page: https://github.com/AllSeeingEyeTolledEweSew/Deluge-Yatfs-Plugin
Author: AllSeeingEyeTolledEweSew
Author-email: allseeingeyetolledewesew@protonmail.com
License: Unlicense
Platform: UNKNOWN
Classifier: Development Status :: 4 - Beta
Classifier: Intended Audience :: End Users/Desktop
Classifier: Environment :: Plugins
Classifier: License :: Public Domain
Classifier: Programming Language :: Python
Classifier: Topic :: Communications :: File Sharing
Classifier: Topic :: System :: Networking
Classifier: Operating System :: OS Independent
